[{"id":"0c2a5138-82af-4c7f-aca9-9913d00734c1","employee_id":"9a7309ed-1877-41e8-ac00-d5b71e0b94d6","basic_salary":180000,"hra":0,"da":0,"ta":0,"medical_allowance":0,"other_allowances":0,"pf":0,"esi":0,"professional_tax":0,"tds":9300,"other_deductions":0,"gross_salary":180000,"net_salary":170700,"effective_from":"2026-03-24","created_at":"2026-02-23 22:57:24.65","updated_at":"2026-03-24 04:17:20.872"},{"id":"4fe0e511-a816-4c80-9a34-b844d3f57a27","employee_id":"800f3ea7-0043-4565-bdec-562a9b9a0d2c","basic_salary":85000,"hra":0,"da":0,"ta":0,"medical_allowance":0,"other_allowances":0,"pf":0,"esi":0,"professional_tax":0,"tds":350,"other_deductions":0,"gross_salary":85000,"net_salary":84650,"effective_from":"2026-05-20","created_at":"2026-04-27 22:29:16.939","updated_at":"2026-05-20 18:09:31.728"},{"id":"540986dc-a18b-4a8f-9d8a-13aa4b606614","employee_id":"a5b5e420-8aa9-4e2d-949b-1558080ffe0c","basic_salary":145000,"hra":0,"da":0,"ta":0,"medical_allowance":0,"other_allowances":0,"pf":0,"esi":0,"professional_tax":0,"tds":5450,"other_deductions":0,"gross_salary":145000,"net_salary":139550,"effective_from":"2026-05-01","created_at":"2026-02-23 23:00:02.216","updated_at":"2026-05-01 20:46:44.743"},{"id":"57ff52f7-dcee-495e-849e-d7e663a8258b","employee_id":"4e919df1-b2a7-4ef7-a98d-dc234887e925","basic_salary":260000,"hra":0,"da":0,"ta":0,"medical_allowance":0,"other_allowances":0,"pf":0,"esi":0,"professional_tax":0,"tds":27300,"other_deductions":0,"gross_salary":260000,"net_salary":232700,"effective_from":"2026-03-24","created_at":"2026-02-23 22:56:57.948","updated_at":"2026-03-24 00:56:20.449"},{"id":"6873a843-c9d3-4fea-851c-9a012b3b6fbd","employee_id":"4024c8d4-cded-4f17-90af-793e377887a8","basic_salary":125000,"hra":0,"da":0,"ta":0,"medical_allowance":0,"other_allowances":0,"pf":0,"esi":0,"professional_tax":0,"tds":3250,"other_deductions":0,"gross_salary":125000,"net_salary":121750,"effective_from":"2026-03-24","created_at":"2026-02-23 22:56:37.373","updated_at":"2026-03-24 04:09:10.767"},{"id":"6d344e5f-4134-4e47-887c-e4c1015ab201","employee_id":"bc09378b-6dfa-4b29-a2dd-1fcce6fb5687","basic_salary":130000,"hra":0,"da":0,"ta":0,"medical_allowance":0,"other_allowances":0,"pf":0,"esi":0,"professional_tax":0,"tds":3800,"other_deductions":0,"gross_salary":130000,"net_salary":126200,"effective_from":"2026-05-04","created_at":"2026-05-01 20:23:05.155","updated_at":"2026-05-04 18:05:34.976"},{"id":"6e1d2d58-6e7f-49ea-8daf-f10106a7b451","employee_id":"f30c58fa-8015-409e-a99c-485c69ab9d98","basic_salary":230000,"hra":0,"da":0,"ta":0,"medical_allowance":0,"other_allowances":0,"pf":0,"esi":0,"professional_tax":0,"tds":20400,"other_deductions":0,"gross_salary":230000,"net_salary":209600,"effective_from":"2026-02-23","created_at":"2026-02-23 22:58:58.271","updated_at":"2026-02-23 23:14:46.491"},{"id":"9565e3b1-1880-4d49-a24b-d122b7552f79","employee_id":"45e08cae-ec3e-4742-b03b-f50348380fce","basic_salary":200000,"hra":0,"da":0,"ta":0,"medical_allowance":0,"other_allowances":0,"pf":0,"esi":0,"professional_tax":0,"tds":13500,"other_deductions":0,"gross_salary":200000,"net_salary":186500,"effective_from":"2026-02-23","created_at":"2026-02-23 22:58:37.932","updated_at":"2026-02-23 23:09:06.224"},{"id":"aedf96db-4acb-41ad-95d8-b8abe287a399","employee_id":"a133c49f-5174-4bc1-bc1a-a313d39deeef","basic_salary":60000,"hra":0,"da":0,"ta":0,"medical_allowance":0,"other_allowances":0,"pf":0,"esi":0,"professional_tax":0,"tds":100,"other_deductions":0,"gross_salary":60000,"net_salary":59900,"effective_from":"2026-03-09","created_at":"2026-02-23 22:57:48.422","updated_at":"2026-03-09 22:44:39.063"},{"id":"c3b3c928-dcf4-420e-a8ec-0f12ef5d7380","employee_id":"d659256c-03f1-4bae-961c-541162c2133a","basic_salary":175000,"hra":0,"da":0,"ta":0,"medical_allowance":0,"other_allowances":0,"pf":0,"esi":0,"professional_tax":0,"tds":8750,"other_deductions":0,"gross_salary":175000,"net_salary":166250,"effective_from":"2026-02-26","created_at":"2026-02-23 22:58:19.219","updated_at":"2026-02-26 20:46:23.899"},{"id":"ede2273e-d6f9-43b3-83dd-9a0236e8ceb4","employee_id":"796f5190-2b91-418b-bc38-0064085051a2","basic_salary":140000,"hra":0,"da":0,"ta":0,"medical_allowance":0,"other_allowances":0,"pf":0,"esi":0,"professional_tax":0,"tds":4900,"other_deductions":0,"gross_salary":140000,"net_salary":135100,"effective_from":"2026-05-04","created_at":"2026-05-01 20:22:52.17","updated_at":"2026-05-04 18:10:08.29"},{"id":"f4d494d3-a1bd-49b6-90f0-84eea0075414","employee_id":"90e74e9d-38f9-42d8-ba37-7e3ab5918735","basic_salary":175000,"hra":0,"da":0,"ta":0,"medical_allowance":0,"other_allowances":0,"pf":0,"esi":0,"professional_tax":0,"tds":8750,"other_deductions":0,"gross_salary":175000,"net_salary":166250,"effective_from":"2026-04-16","created_at":"2026-02-23 22:59:25.535","updated_at":"2026-04-16 01:37:52.229"},{"id":"f846efee-2e20-4789-b0f6-f3e5c8cc1f5c","employee_id":"e094c4c9-82b5-4ab7-8994-657c28111f1f","basic_salary":230000,"hra":0,"da":0,"ta":0,"medical_allowance":0,"other_allowances":0,"pf":0,"esi":0,"professional_tax":0,"tds":20400,"other_deductions":0,"gross_salary":230000,"net_salary":209600,"effective_from":"2026-02-24","created_at":"2026-02-18 19:00:28.848","updated_at":"2026-02-24 22:28:26.874"}]